setup.cfg
setup.py
pymacds/__init__.py
pymacds.egg-info/PKG-INFO
pymacds.egg-info/SOURCES.txt
pymacds.egg-info/dependency_links.txt
pymacds.egg-info/requires.txt
pymacds.egg-info/top_level.txt