Metadata-Version: 1.0
Name: pymacds
Version: 0.2
Summary: Python wrappers for Mac OS X DirectoryService functions.
Home-page: https://github.com/tarak/pymacds
Author: Nigel Kersten
Author-email: nigelk@google.com
License: UNKNOWN
Platform: UNKNOWN
